README.md
setup.py
bit/__init__.py
bit/bit-wise.py
bit_wise.egg-info/PKG-INFO
bit_wise.egg-info/SOURCES.txt
bit_wise.egg-info/dependency_links.txt
bit_wise.egg-info/top_level.txt