Metadata-Version: 2.1
Name: bit-wise
Version: 0.0.1
Summary: Bitwise functions
Home-page: https://github.com/DataScienceStep/bit
Author: DataScienceStep
Author-email: DataScienceStep@GMail.com
License: UNKNOWN
Platform: UNKNOWN
